Workbook

Sheet Read Me
B2: ALAGA FLEX — SKU #1 Financial Model
B3: Dog joint supplement (soft chew) · Philippines import & D2C/wholesale launch
B5: HOW TO USE THIS MODEL
B6: 1. Go to the Assumptions tab. Every cell you should touch is BLUE TEXT ON YELLOW.
B7: 2. Everything else is a formula — leave it alone and it will recalculate.
B8: 3. Landed Cost compares a US (NASC) supplier against a China supplier side by side.
B9: 4. Pick your supplier lane in Assumptions (cell B10) — the whole model follows it.
B10: 5. Monthly Model runs 24 months. Scenarios shows conservative / base / upside payback.
B12: COLOUR KEY
B13: Blue text on yellow = your input. Change these.
B14: Black text = calculated. Do not overwrite.
B15: Green text = pulled from another tab in this workbook.
... B39: Note too that US-lane wholesale margin lands at ~29%, just under the 30% screen.

Sheet Assumptions
B2: ASSUMPTIONS — edit the yellow cells only
B4: MACRO & SETUP
B5: PHP per USD | C5: 61.44 | D5: Verified: ~61.44, mid-Aug 2026. Stress at 65.
B6: Business registration (DTI/BIR/permits) | C6: 50000 | D6: Estimate
B7: Brand, packaging design, label artwork | C7: 120000 | D7: Estimate — see launch pack
B8: BAI registration: consultant + dossier + stability | C8: 300000 | D8: ESTIMATE. Get a real quote. Kill if >500,000.
B9: Registration lead time (months) | C9: 9 | D9: Estimate 6–12. Sell grooming SKUs meanwhile.
B11: SUPPLIER LANE
B12: Lane: 1 = US/NASC, 2 = China | C12: 1 | D12: Drives Landed Cost. US wins on BAI paperwork.
B13: Selected lane name | C13: =IF(C12=1,"US / NASC","China")
B15: PRODUCT & PRICING (per 60-count jar)
B16: Retail price (VAT-inclusive) | C16: 1450 | D16: ESTIMATE. Imported joint supplements ~1,200–1,800.
B17: Wholesale price to salons/pet shops | C17: 800 | D17: Estimate ~55% of retail
B18: Share of units sold direct (e-commerce) | C18: 0.7 | D18: Balance goes wholesale
B19: VAT registered? 1 = yes, 0 = no | C19: 1 | D19: If yes, import VAT is creditable, not a cost
B20: VAT rate | C20: 0.12 | D20: Statutory 12%
B22: DEMAND & RETENTION
B23: New customers, month 1 | C23: 45 | D23: Estimate
B24: Monthly growth in new customers | C24: 0.18 | D24: Estimate — compounding, capped below
B25: Cap on new customers per month | C25: 420 | D25: Estimate of channel ceiling
B26: First-time buyers who become repeaters | C26: 0.35 | D26: THE KEY NUMBER. Kill play if <15% by month 4.
B27: Monthly retention of repeat base | C27: 0.78 | D27: Estimate
B28: Orders per month per active repeater | C28: 0.55 | D28: 0.5 = reorders every 2 months
B29: Demand scenario multiplier | C29: 1 | D29: 1.0 = base. Scenarios tab uses 0.6 / 1.0 / 1.5.
B31: CHANNEL & OPERATING COSTS
B32: E-commerce platform fees (% of retail) | C32: 0.13 | D32: Shopee/TikTok commission + payment
B33: Marketing / CAC (% of direct revenue) | C33: 0.15 | D33: Affiliate + live-selling
B34: Manager salary (monthly) | C34: 35000 | D34: Owner-with-manager model
B35: Other fixed monthly (3PL, storage, tools) | C35: 22000 | D35: Estimate
B36: Product returns / spoilage allowance | C36: 0.05 | D36: Tropical climate — watch soft chews
B38: INVENTORY & WORKING CAPITAL
B39: Contingency buffer on total capital | C39: 0.2 | D39: Per operating manual
B40: Initial order quantity comes from the Landed Cost tab (MOQ).

Sheet Landed Cost
B2: LANDED COST — US/NASC vs China
B3: Per 60-count jar, landed Manila, first purchase order
C5: US / NASC | D5: China | E5: Note
B6: FOB price per unit (USD) | C6: 7 | D6: 4 | E6: ESTIMATE — replace with RFQ quotes
B7: Minimum order quantity (units) | C7: 2500 | D7: 1000 | E7: US MOQs typically higher
B8: Freight + insurance (% of FOB value) | C8: 0.12 | D8: 0.1 | E8: Estimate; China closer, cheaper
B9: Customs duty rate | C9: 0.03 | D9: 0 | E9: China may qualify ACFTA Form E at 0%. CONFIRM HS code with broker.
B10: Brokerage, handling, local haulage | C10: 25000 | D10: 25000 | E10: Per shipment, estimate
B12: FOB value (USD) | C12: =C6*C7 | D12: =D6*D7
B13: CIF value (USD) | C13: =C12*(1+C8) | D13: =D12*(1+D8)
B14: CIF value (PHP) | C14: =C13*Assumptions!$C$5 | D14: =D13*Assumptions!$C$5
B15: Customs duty (PHP) | C15: =C14*C9 | D15: =D14*D9
B16: Import VAT (PHP) | C16: =(C14+C15)*Assumptions!$C$20 | D16: =(D14+D15)*Assumptions!$C$20 | E16: Creditable if VAT-registered — excluded from cost below
B17: Brokerage & handling (PHP) | C17: =C10 | D17: =D10
B18: TOTAL SHIPMENT COST (PHP, ex-VAT if registered) | C18: =C14+C15+C17+IF(Assumptions!$C$19=1,0,C16) | D18: =D14+D15+D17+IF(Assumptions!$C$19=1,0,D16)
B19: LANDED COST PER UNIT (PHP) | C19: =C18/C7 | D19: =D18/D7 | E19: The number that matters
B21: SELECTED LANE (from Assumptions C12)
B22: Landed cost per unit | C22: =IF(Assumptions!$C$12=1,C19,D19)
B23: Initial order quantity (MOQ) | C23: =IF(Assumptions!$C$12=1,C7,D7)
B24: Initial inventory investment | C24: =IF(Assumptions!$C$12=1,C18,D18)
B25: Gross margin, direct retail (ex-VAT) | C25: =1-C22/(Assumptions!$C$16/(1+Assumptions!$C$20*Assumptions!$C$19)) | E25: Target 60%+ per operating manual
B26: Gross margin, wholesale (ex-VAT) | C26: =1-C22/(Assumptions!$C$17/(1+Assumptions!$C$20*Assumptions!$C$19)) | E26: Target 30%+ per operating manual
B28: READING THIS COMPARISON
B29: • US/NASC advantage is PAPERWORK: an FDA-registered facility can issue a Certificate of Free Sale,
B30: the exact document BAI requires, and NASC certification strengthens the dossier.
B31: • China advantage is CASH: at these placeholder prices, far lower landed cost and a much smaller MOQ.
B32: • AT THESE PLACEHOLDER NUMBERS THE CHINA LANE WINS ON THE MATH — payback ~15 months versus
B33: beyond 24 months for the US lane, which also lands at ~29% wholesale margin, under the 30% screen.
B34: • That verdict is only as good as the placeholder FOB and MOQ. The US lane becomes competitive at
B35: roughly FOB $5.00 or MOQ 1,500 — which is precisely why the RFQ asks for tiered pricing.
B36: • SO: do not choose the lane from this sheet. Get the quotes, put the real numbers in, then choose.
B37: • If a China supplier can produce a Certificate of Free Sale and Zone IVb stability data, it wins
B38: outright. If none can, the decision becomes: pay the US premium, or have no registration at all.

Sheet Monthly Model
B2: MONTHLY MODEL — 24 MONTHS
B3: Month 1 = first month of sales. Registration runs in parallel before this.
B5: Month | C5: 1 | D5: 2 | E5: 3 | F5: 4 | G5: 5 | H5: 6 | I5: 7 | J5: 8 | K5: 9 | L5: 10 | M5: 11 | N5: 12 | O5: 13 | P5: 14 | Q5: 15 | R5: 16 | S5: 17 | T5: 18 | U5: 19 | V5: 20 | W5: 21 | X5: 22 | Y5: 23 | Z5: 24
B7: CUSTOMERS
B8: New customers | C8: =ROUND(Assumptions!$C$23*Assumptions!$C$29,0) | D8: =ROUND(MIN(C8*(1+Assumptions!$C$24),Assumptions!$C$25*Assumptions!$C$29),0) | E8: =ROUND(MIN(D8*(1+Assumptions!$C$24),Assumptions!$C$25*Assumptions!$C$29),0) | F8: =ROUND(MIN(E8*(1+Assumptions!$C$24),Assumptions!$C$25*Assumptions!$C$29),0) | G8: =ROUND(MIN(F8*(1+Assumptions!$C$24),Assumptions!$C$25*Assumptions!$C$29),0) | H8: =ROUND(MIN(G8*(1+Assumptions!$C$24),Assumptions!$C$25*Assumptions!$C$29),0) | I8: =ROUND(MIN(H8*(1+Assumptions!$C$24),Assumptions!$C$25*Assumptions!$C$29),0) | J8: =ROUND(MIN(I8*(1+Assumptions!$C$24),Assumptions!$C$25*Assumptions!$C$29),0) | K8: =ROUND(MIN(J8*(1+Assumptions!$C$24),Assumptions!$C$25*Assumptions!$C$29),0) | ... Z8: =ROUND(MIN(Y8*(1+Assumptions!$C$24),Assumptions!$C$25*Assumptions!$C$29),0)
B9: Active repeat base | C9: =0 | D9: =ROUND((C9+C8*Assumptions!$C$26)*Assumptions!$C$27,0) | E9: =ROUND((D9+D8*Assumptions!$C$26)*Assumptions!$C$27,0) | F9: =ROUND((E9+E8*Assumptions!$C$26)*Assumptions!$C$27,0) | G9: =ROUND((F9+F8*Assumptions!$C$26)*Assumptions!$C$27,0) | H9: =ROUND((G9+G8*Assumptions!$C$26)*Assumptions!$C$27,0) | I9: =ROUND((H9+H8*Assumptions!$C$26)*Assumptions!$C$27,0) | J9: =ROUND((I9+I8*Assumptions!$C$26)*Assumptions!$C$27,0) | K9: =ROUND((J9+J8*Assumptions!$C$26)*Assumptions!$C$27,0) | ... Z9: =ROUND((Y9+Y8*Assumptions!$C$26)*Assumptions!$C$27,0)
B10: Repeat orders | C10: =0 | D10: =D9*Assumptions!$C$28 | E10: =E9*Assumptions!$C$28 | F10: =F9*Assumptions!$C$28 | G10: =G9*Assumptions!$C$28 | H10: =H9*Assumptions!$C$28 | I10: =I9*Assumptions!$C$28 | J10: =J9*Assumptions!$C$28 | K10: =K9*Assumptions!$C$28 | ... Z10: =Z9*Assumptions!$C$28
B11: Total units sold | C11: =C8+C10 | D11: =D8+D10 | E11: =E8+E10 | F11: =F8+F10 | G11: =G8+G10 | H11: =H8+H10 | I11: =I8+I10 | J11: =J8+J10 | ... Z11: =Z8+Z10
B13: REVENUE
B14: Direct units | C14: =C11*Assumptions!$C$18 | D14: =D11*Assumptions!$C$18 | E14: =E11*Assumptions!$C$18 | F14: =F11*Assumptions!$C$18 | G14: =G11*Assumptions!$C$18 | H14: =H11*Assumptions!$C$18 | I14: =I11*Assumptions!$C$18 | J14: =J11*Assumptions!$C$18 | ... Z14: =Z11*Assumptions!$C$18
B15: Wholesale units | C15: =C11*(1-Assumptions!$C$18) | D15: =D11*(1-Assumptions!$C$18) | E15: =E11*(1-Assumptions!$C$18) | F15: =F11*(1-Assumptions!$C$18) | G15: =G11*(1-Assumptions!$C$18) | H15: =H11*(1-Assumptions!$C$18) | I15: =I11*(1-Assumptions!$C$18) | J15: =J11*(1-Assumptions!$C$18) | ... Z15: =Z11*(1-Assumptions!$C$18)
B16: Direct revenue (ex-VAT) | C16: =C14*Assumptions!$C$16/(1+Assumptions!$C$20*Assumptions!$C$19) | D16: =D14*Assumptions!$C$16/(1+Assumptions!$C$20*Assumptions!$C$19) | E16: =E14*Assumptions!$C$16/(1+Assumptions!$C$20*Assumptions!$C$19) | F16: =F14*Assumptions!$C$16/(1+Assumptions!$C$20*Assumptions!$C$19) | G16: =G14*Assumptions!$C$16/(1+Assumptions!$C$20*Assumptions!$C$19) | H16: =H14*Assumptions!$C$16/(1+Assumptions!$C$20*Assumptions!$C$19) | I16: =I14*Assumptions!$C$16/(1+Assumptions!$C$20*Assumptions!$C$19) | J16: =J14*Assumptions!$C$16/(1+Assumptions!$C$20*Assumptions!$C$19) | ... Z16: =Z14*Assumptions!$C$16/(1+Assumptions!$C$20*Assumptions!$C$19)
B17: Wholesale revenue (ex-VAT) | C17: =C15*Assumptions!$C$17/(1+Assumptions!$C$20*Assumptions!$C$19) | D17: =D15*Assumptions!$C$17/(1+Assumptions!$C$20*Assumptions!$C$19) | E17: =E15*Assumptions!$C$17/(1+Assumptions!$C$20*Assumptions!$C$19) | F17: =F15*Assumptions!$C$17/(1+Assumptions!$C$20*Assumptions!$C$19) | G17: =G15*Assumptions!$C$17/(1+Assumptions!$C$20*Assumptions!$C$19) | H17: =H15*Assumptions!$C$17/(1+Assumptions!$C$20*Assumptions!$C$19) | I17: =I15*Assumptions!$C$17/(1+Assumptions!$C$20*Assumptions!$C$19) | J17: =J15*Assumptions!$C$17/(1+Assumptions!$C$20*Assumptions!$C$19) | ... Z17: =Z15*Assumptions!$C$17/(1+Assumptions!$C$20*Assumptions!$C$19)
B18: Total revenue | C18: =C16+C17 | D18: =D16+D17 | E18: =E16+E17 | F18: =F16+F17 | G18: =G16+G17 | H18: =H16+H17 | I18: =I16+I17 | J18: =J16+J17 | ... Z18: =Z16+Z17
B20: COSTS
B21: COGS (landed) | C21: =C11*'Landed Cost'!$C$22 | D21: =D11*'Landed Cost'!$C$22 | E21: =E11*'Landed Cost'!$C$22 | F21: =F11*'Landed Cost'!$C$22 | G21: =G11*'Landed Cost'!$C$22 | H21: =H11*'Landed Cost'!$C$22 | I21: =I11*'Landed Cost'!$C$22 | J21: =J11*'Landed Cost'!$C$22 | ... Z21: =Z11*'Landed Cost'!$C$22
B22: Returns / spoilage | C22: =C18*Assumptions!$C$36 | D22: =D18*Assumptions!$C$36 | E22: =E18*Assumptions!$C$36 | F22: =F18*Assumptions!$C$36 | G22: =G18*Assumptions!$C$36 | H22: =H18*Assumptions!$C$36 | I22: =I18*Assumptions!$C$36 | J22: =J18*Assumptions!$C$36 | ... Z22: =Z18*Assumptions!$C$36
B23: Gross profit | C23: =C18-C21-C22 | D23: =D18-D21-D22 | E23: =E18-E21-E22 | F23: =F18-F21-F22 | G23: =G18-G21-G22 | H23: =H18-H21-H22 | I23: =I18-I21-I22 | J23: =J18-J21-J22 | ... Z23: =Z18-Z21-Z22
B24: Platform fees | C24: =C16*Assumptions!$C$32 | D24: =D16*Assumptions!$C$32 | E24: =E16*Assumptions!$C$32 | F24: =F16*Assumptions!$C$32 | G24: =G16*Assumptions!$C$32 | H24: =H16*Assumptions!$C$32 | I24: =I16*Assumptions!$C$32 | J24: =J16*Assumptions!$C$32 | ... Z24: =Z16*Assumptions!$C$32
B25: Marketing / CAC | C25: =C16*Assumptions!$C$33 | D25: =D16*Assumptions!$C$33 | E25: =E16*Assumptions!$C$33 | F25: =F16*Assumptions!$C$33 | G25: =G16*Assumptions!$C$33 | H25: =H16*Assumptions!$C$33 | I25: =I16*Assumptions!$C$33 | J25: =J16*Assumptions!$C$33 | ... Z25: =Z16*Assumptions!$C$33
B26: Manager salary | C26: =Assumptions!$C$34 | D26: =Assumptions!$C$34 | E26: =Assumptions!$C$34 | F26: =Assumptions!$C$34 | G26: =Assumptions!$C$34 | H26: =Assumptions!$C$34 | I26: =Assumptions!$C$34 | J26: =Assumptions!$C$34 | ... Z26: =Assumptions!$C$34
B27: Other fixed costs | C27: =Assumptions!$C$35 | D27: =Assumptions!$C$35 | E27: =Assumptions!$C$35 | F27: =Assumptions!$C$35 | G27: =Assumptions!$C$35 | H27: =Assumptions!$C$35 | I27: =Assumptions!$C$35 | J27: =Assumptions!$C$35 | ... Z27: =Assumptions!$C$35
B28: Total operating costs | C28: =SUM(C24:C27) | D28: =SUM(D24:D27) | E28: =SUM(E24:E27) | F28: =SUM(F24:F27) | G28: =SUM(G24:G27) | H28: =SUM(H24:H27) | I28: =SUM(I24:I27) | J28: =SUM(J24:J27) | ... Z28: =SUM(Z24:Z27)
B30: PROFIT & CASH
B31: EBITDA | C31: =C23-C28 | D31: =D23-D28 | E31: =E23-E28 | F31: =F23-F28 | G31: =G23-G28 | H31: =H23-H28 | I31: =I23-I28 | J31: =J23-J28 | ... Z31: =Z23-Z28
B32: Cumulative EBITDA | C32: =C31 | D32: =C32+D31 | E32: =D32+E31 | F32: =E32+F31 | G32: =F32+G31 | H32: =G32+H31 | I32: =H32+I31 | J32: =I32+J31 | K32: =J32+K31 | ... Z32: =Y32+Z31
B33: Cumulative cash vs capital | C33: =C32-'Scenarios & Payback'!$C$8 | D33: =C33+D31 | E33: =D33+E31 | F33: =E33+F31 | G33: =F33+G31 | H33: =G33+H31 | I33: =H33+I31 | J33: =I33+J31 | K33: =J33+K31 | ... Z33: =Y33+Z31
B34: Payback reached this month? | C34: =IF(C33>=0,"YES","") | D34: =IF(AND(D33>=0,C33<0),"YES","") | E34: =IF(AND(E33>=0,D33<0),"YES","") | F34: =IF(AND(F33>=0,E33<0),"YES","") | G34: =IF(AND(G33>=0,F33<0),"YES","") | H34: =IF(AND(H33>=0,G33<0),"YES","") | I34: =IF(AND(I33>=0,H33<0),"YES","") | J34: =IF(AND(J33>=0,I33<0),"YES","") | K34: =IF(AND(K33>=0,J33<0),"YES","") | ... Z34: =IF(AND(Z33>=0,Y33<0),"YES","")
B35: EBITDA positive flag | C35: =IF(C31>0,1,0) | D35: =IF(D31>0,1,0) | E35: =IF(E31>0,1,0) | F35: =IF(F31>0,1,0) | G35: =IF(G31>0,1,0) | H35: =IF(H31>0,1,0) | I35: =IF(I31>0,1,0) | J35: =IF(J31>0,1,0) | ... Z35: =IF(Z31>0,1,0)

Sheet Scenarios & Payback
B2: CAPITAL REQUIRED & PAYBACK
B4: TOTAL CAPITAL REQUIRED
B5: Initial inventory (first PO at MOQ) | C5: ='Landed Cost'!C24
B6: BAI registration + business setup + brand | C6: =Assumptions!C6+Assumptions!C7+Assumptions!C8 | F6: Registration is the long pole — start it first
B7: Contingency buffer | C7: =(C5+C6)*Assumptions!C39
B8: TOTAL CAPITAL REQUIRED | C8: =SUM(C5:C7) | F8: Screen: must sit inside PHP 500,000 – 2,500,000
B9: Fits capital screen? | C9: =IF(AND(C8>=500000,C8<=2500000),"YES — inside range","NO — outside PHP 0.5M-2.5M")
B11: UNIT ECONOMICS (selected lane)
B12: Landed cost per unit | C12: ='Landed Cost'!C22
B13: Retail price (VAT-inclusive) | C13: =Assumptions!C16
B14: Gross margin — direct | C14: ='Landed Cost'!C25 | F14: Manual target: 60%+
B15: Gross margin — wholesale | C15: ='Landed Cost'!C26 | F15: Manual target: 30%+
B16: Contribution per direct unit (after fees & CAC) | C16: =Assumptions!C16/(1+Assumptions!C20*Assumptions!C19)*(1-Assumptions!C32-Assumptions!C33)-'Landed Cost'!C22
B18: 24-MONTH RESULT AT CURRENT SETTINGS
B19: Total units sold | C19: =SUM('Monthly Model'!C11:Z11)
B20: Total revenue | C20: =SUM('Monthly Model'!C18:Z18)
B21: Total EBITDA | C21: =SUM('Monthly Model'!C31:Z31)
B22: Month EBITDA turns positive | C22: =IFERROR(MATCH(1,'Monthly Model'!C35:Z35,0),"not within 24 months")
B23: Payback month (cumulative cash ≥ capital) | C23: =IFERROR(MATCH("YES",'Monthly Model'!C34:Z34,0),"not within 24 months") | F23: Manual screen: 24–30 months or better
B25: SCENARIOS
B26: Change Assumptions!C29 to the multiplier and re-read row 23.
B27: Scenario | C27: Conservative | D27: Base | E27: Upside
B28: Demand multiplier to enter in Assumptions!C29 | C28: 0.6 | D28: 1 | E28: 1.5
B30: KILL CRITERIA — abandon or renegotiate if any is true
B31: • Landed cost per unit exceeds PHP 600 (check cell C12 above).
B32: • Cohort repeat rate is below 15% by month 4 of selling.
B33: • Returns or spoilage exceed 8% — soft chews failing in tropical humidity.
B34: • BAI registration quote exceeds PHP 500,000 per SKU, or 12 months.
B35: • No supplier can produce GMP certificate + Certificate of Free Sale at an MOQ under PHP 300,000.
